oss2/__init__.py
oss2/api.py
oss2/auth.py
oss2/compat.py
oss2/defaults.py
oss2/exceptions.py
oss2/http.py
oss2/iterators.py
oss2/models.py
oss2/resumable.py
oss2/task_queue.py
oss2/utils.py
oss2/xml_utils.py
pw_oss2-2.4.0.dist-info/DESCRIPTION.rst
pw_oss2-2.4.0.dist-info/METADATA
pw_oss2-2.4.0.dist-info/RECORD
pw_oss2-2.4.0.dist-info/WHEEL
pw_oss2-2.4.0.dist-info/metadata.json
pw_oss2-2.4.0.dist-info/top_level.txt
